flow/__init__.py
flow/grapy/__init__.py
flow_grapy-0.0.1.dist-info/LICENSE
flow_grapy-0.0.1.dist-info/METADATA
flow_grapy-0.0.1.dist-info/WHEEL
flow_grapy-0.0.1.dist-info/top_level.txt
flow_grapy-0.0.1.dist-info/RECORD
