Metadata-Version: 2.1
Name: flow-grapy
Version: 0.0.1
Summary: FlowGrapy is a framework that can make the flow of data simple and logical.
Author-email: jiunbae.dev@gmail.com
Maintainer-email: jiunbae.dev@gmail.com
Keywords: flow,graph,grapy,data
Classifier: License :: OSI Approved :: BSD License
Classifier: Programming Language :: Python :: 3
Classifier: Programming Language :: Python :: 3.9
Requires-Python: >=3.9
License-File: LICENSE
Provides-Extra: dev
Requires-Dist: isort ; extra == 'dev'
Requires-Dist: black ; extra == 'dev'
Requires-Dist: flake8 ; extra == 'dev'
Requires-Dist: pylint ; extra == 'dev'
Requires-Dist: pyright ; extra == 'dev'
Requires-Dist: pre-commit ; extra == 'dev'
Provides-Extra: test
Requires-Dist: tox ; extra == 'test'
Requires-Dist: pytest (>=7.0.0) ; extra == 'test'
Requires-Dist: pytest-cov ; extra == 'test'
Requires-Dist: pytest-asyncio ; extra == 'test'
